maple0705/SAR_Logic/RTL/SAR_LOGIC.v
// SARロジック
// 動作周波数(1bit A/Dあたりの時間) : 8MHz
//
// COMP_OUT : ラッチ後のコンパレータ出力(コンパレータに入るCLKがLowになってもコンパレータ出力が変動しないということ)
// DIGITAL_OUT : 1bit A/D結果
// COMP_CLK : コンパレータに入力するCLK(コンパレータが電圧比較するタイミングでSARロジックがコンパレータのCLK端子に信号を入れる)
// SC : CDACの容量のコンパレータ側端子をGNDに落とすSW。HIGHでGNDに落とす想定
// SDAC : CDACの容量にVrefを入力するかGNDを入力するか決めるSW。LOWでGNDを入力、HIGHでVrefを入力する想定。
//        BIT_ADC+1個のSW。MSBがCDACの最大の容量、LSBが最小の容量に対応。
// EOC : End of conversion signal
// CLK : PLL出力CLK(48MHz)
// XRST : 非同期Reset信号
// VDD : 電源電圧
// VSS : GND
//module SAR_LOGIC(COMP_OUT, DIGITAL_OUT, COMP_CLK, SC, SD, S0, S1, S2, S3, S4, S5, S6, S7, CLK, XRST, VDD, VSS);
//module SAR_LOGIC(COMP_OUT, DIGITAL_OUT, COMP_CLK, SC, SDAC, CLK, XRST, vdda1, vssd1);
module SAR_LOGIC(COMP_OUT, DIGITAL_OUT, COMP_CLK, SC, SDAC, EOC, CLK, XRST);
    input COMP_OUT;
    input CLK, XRST;
    output COMP_CLK, SC, EOC;
    output [`BIT_ADC-1:0] DIGITAL_OUT;
    output [`BIT_ADC:0] SDAC;

    reg COMP_CLK, SC, EOC;
    reg [`BIT_ADC-1:0] DIGITAL_OUT;
    reg [`BIT_ADC:0] SDAC, SDAC_NEXT;
    reg [2:0] state;    // 48MHz / 8MHz = 6 なのでバス幅3bit
    reg [2:0] ADCount;  // 1bit A/Dが完了するごとに+1。 6bit A/Dなのでバス幅3bit

    // state transition
    always @(posedge CLK or negedge XRST) begin
        if( XRST == `LOW ) begin
            state <= 0;
        end else if( state == 3'd6 ) begin
            state <= 1;
        end else begin
            state <= state + 1;
        end
    end

    // count the number of A/D times
    always @(posedge CLK or negedge XRST) begin
        if( XRST == `LOW ) begin
            ADCount <= 0;
        end else if( state == 3'd6 ) begin
            if ( ADCount == `BIT_ADC - 1 ) begin
                ADCount <= 0;
            end else begin
                ADCount <= ADCount + 1;
            end
        end
    end

    // each state operation
    always @(posedge CLK or negedge XRST) begin
        if( XRST == `LOW ) begin
            DIGITAL_OUT <= 0;
            COMP_CLK <= `LOW;
            SC <= `HIGH;
            EOC <= `LOW;
            SDAC <= 0;
            SDAC_NEXT <= 1 << `BIT_ADC;  // only MSB is HIGH, meaning Vinn = Vref / 2
        end else if( state == 3'd1) begin
            // CDAC Reset, CLK@Comparator Low
            COMP_CLK <= `LOW;
            SC <= `HIGH;
            SDAC <= 0;
            EOC <= `LOW;
        end else if( state == 3'd2) begin
            // Sc OFF(Vinn = Hi-Z)
            SC <= `LOW;
        end else if( state == 3'd3) begin
            // ref GEN.
            SDAC <= SDAC_NEXT;
        end else if( state == 3'd4) begin
            // CLK@Comparator High
            COMP_CLK <= `HIGH;
        end else if( state == 3'd5) begin
            DIGITAL_OUT <= {DIGITAL_OUT[`BIT_ADC-2:0], COMP_OUT};
            SDAC_NEXT <= next_SDAC(COMP_OUT, ADCount, SDAC);
        end else if( state == 3'd6) begin
            if ( ADCount == `BIT_ADC - 1 ) begin
                EOC <= `HIGH;
            end
        end
    end

    // determin next SDAC(SW state of CDAC) depenging on COMP_OUT(actually output of latch)
    function [`BIT_ADC:0] next_SDAC;
        input COMP_OUT;
        input [2:0] ADCount;
        input [`BIT_ADC:0] SDAC_now;

        if ( ADCount == `BIT_ADC - 1 ) begin    // LSB A/D converting now
            next_SDAC = 1 << `BIT_ADC;          // only MSB is HIGH, meaning Vinn = Vref / 2
        end else if( COMP_OUT == 0 ) begin
            next_SDAC = SDAC_now;
            next_SDAC[`BIT_ADC - ADCount] = 0;
            next_SDAC[`BIT_ADC - (ADCount + 1)] = 1;
        end else begin
            next_SDAC = SDAC_now;
            next_SDAC[`BIT_ADC - (ADCount + 1)] = 1;
        end

    endfunction
endmodule

maple0705/SAR_Logic/RTL/SAR_LOGIC_tb.v
`define HIGH 1'b1
`define LOW 1'b0
`define BIT_ADC 4'd6

module SAR_LOGIC_tb;
    reg CLK = 1'b0;
    reg COMP_OUT = 1'b1;
    reg XRST = 1'b1;
    wire [`BIT_ADC-1:0] DIGITAL_OUT;
    wire COMP_CLK;
    wire SC;
    wire EOC;
    wire [`BIT_ADC:0] SDAC;

    initial begin
        $dumpfile("wave_SAR_Logic.vcd");
        $dumpvars(0, DUT);
    end

    always #2 begin
        CLK <= ~CLK;
    end

    SAR_LOGIC DUT(
        .COMP_OUT (COMP_OUT),       // 1bit input
        .DIGITAL_OUT (DIGITAL_OUT), // 1bit output
        .COMP_CLK (COMP_CLK),       // 1bit output
        .SC (SC),                   // 1bit output
        .SDAC (SDAC),               // 9bit output
        .EOC (EOC),                 // 1bit output
        .CLK (CLK),                 // 1bit input
        .XRST (XRST)                // 1bit input
    );

    initial begin
        #2
        XRST = 1'b0;
        #3
        XRST = 1'b1;

        #43
        COMP_OUT = 0;
        #400
        $finish;
    end
endmodule

maple0705/SAR_Logic/RTL/wave_SAR_Logic.vcd
$date
	Thu Apr 11 00:17:50 2024
$end
$version
	Icarus Verilog
$end
$timescale
	1s
$end
$scope module SAR_LOGIC_tb $end
$scope module DUT $end
$var wire 1 ! CLK $end
$var wire 1 " COMP_OUT $end
$var wire 1 # XRST $end
$var reg 3 $ ADCount [2:0] $end
$var reg 1 % COMP_CLK $end
$var reg 6 & DIGITAL_OUT [5:0] $end
$var reg 1 ' EOC $end
$var reg 1 ( SC $end
$var reg 7 ) SDAC [6:0] $end
$var reg 7 * SDAC_NEXT [6:0] $end
$var reg 3 + state [2:0] $end
$scope function next_SDAC $end
$var reg 3 , ADCount [2:0] $end
$var reg 1 - COMP_OUT $end
$var reg 7 . SDAC_now [6:0] $end
$upscope $end
$upscope $end
$upscope $end
$enddefinitions $end
#0
$dumpvars
bx .
x-
bx ,
bx +
bx *
bx )
x(
x'
bx &
x%
bx $
1#
1"
0!
$end
#2
b0 +
b0 $
b1000000 *
b0 )
0'
1(
0%
b0 &
1!
0#
#4
0!
#5
1#
#6
b1 +
1!
#8
0!
#10
b10 +
1!
#12
0!
#14
b11 +
0(
1!
#16
0!
#18
b1000000 )
b100 +
1!
#20
0!
#22
b101 +
1%
1!
#24
0!
#26
b1100000 *
b1 &
b110 +
1-
b0 ,
b1000000 .
1!
#28
0!
#30
b1 +
b1 $
1!
#32
0!
#34
b0 )
1(
0%
b10 +
1!
#36
0!
#38
b11 +
0(
1!
#40
0!
#42
b1100000 )
b100 +
1!
#44
0!
#46
b101 +
1%
1!
#48
0!
0"
#50
b1010000 *
b10 &
b110 +
0-
b1 ,
b1100000 .
1!
#52
0!
#54
b1 +
b10 $
1!
#56
0!
#58
b0 )
1(
0%
b10 +
1!
#60
0!
#62
b11 +
0(
1!
#64
0!
#66
b1010000 )
b100 +
1!
#68
0!
#70
b101 +
1%
1!
#72
0!
#74
b1001000 *
b100 &
b110 +
b10 ,
b1010000 .
1!
#76
0!
#78
b1 +
b11 $
1!
#80
0!
#82
b0 )
1(
0%
b10 +
1!
#84
0!
#86
b11 +
0(
1!
#88
0!
#90
b1001000 )
b100 +
1!
#92
0!
#94
b101 +
1%
1!
#96
0!
#98
b1000100 *
b1000 &
b110 +
b11 ,
b1001000 .
1!
#100
0!
#102
b1 +
b100 $
1!
#104
0!
#106
b0 )
1(
0%
b10 +
1!
#108
0!
#110
b11 +
0(
1!
#112
0!
#114
b1000100 )
b100 +
1!
#116
0!
#118
b101 +
1%
1!
#120
0!
#122
b1000010 *
b10000 &
b110 +
b100 ,
b1000100 .
1!
#124
0!
#126
b1 +
b101 $
1!
#128
0!
#130
b0 )
1(
0%
b10 +
1!
#132
0!
#134
b11 +
0(
1!
#136
0!
#138
b1000010 )
b100 +
1!
#140
0!
#142
b101 +
1%
1!
#144
0!
#146
b1000000 *
b100000 &
b110 +
b101 ,
b1000010 .
1!
#148
0!
#150
b1 +
b0 $
1'
1!
#152
0!
#154
0'
b0 )
1(
0%
b10 +
1!
#156
0!
#158
b11 +
0(
1!
#160
0!
#162
b1000000 )
b100 +
1!
#164
0!
#166
b101 +
1%
1!
#168
0!
#170
b100000 *
b0 &
b110 +
b0 ,
b1000000 .
1!
#172
0!
#174
b1 +
b1 $
1!
#176
0!
#178
b0 )
1(
0%
b10 +
1!
#180
0!
#182
b11 +
0(
1!
#184
0!
#186
b100000 )
b100 +
1!
#188
0!
#190
b101 +
1%
1!
#192
0!
#194
b10000 *
b110 +
b1 ,
b100000 .
1!
#196
0!
#198
b1 +
b10 $
1!
#200
0!
#202
b0 )
1(
0%
b10 +
1!
#204
0!
#206
b11 +
0(
1!
#208
0!
#210
b10000 )
b100 +
1!
#212
0!
#214
b101 +
1%
1!
#216
0!
#218
b1000 *
b110 +
b10 ,
b10000 .
1!
#220
0!
#222
b1 +
b11 $
1!
#224
0!
#226
b0 )
1(
0%
b10 +
1!
#228
0!
#230
b11 +
0(
1!
#232
0!
#234
b1000 )
b100 +
1!
#236
0!
#238
b101 +
1%
1!
#240
0!
#242
b100 *
b110 +
b11 ,
b1000 .
1!
#244
0!
#246
b1 +
b100 $
1!
#248
0!
#250
b0 )
1(
0%
b10 +
1!
#252
0!
#254
b11 +
0(
1!
#256
0!
#258
b100 )
b100 +
1!
#260
0!
#262
b101 +
1%
1!
#264
0!
#266
b10 *
b110 +
b100 ,
b100 .
1!
#268
0!
#270
b1 +
b101 $
1!
#272
0!
#274
b0 )
1(
0%
b10 +
1!
#276
0!
#278
b11 +
0(
1!
#280
0!
#282
b10 )
b100 +
1!
#284
0!
#286
b101 +
1%
1!
#288
0!
#290
b1000000 *
b110 +
b101 ,
b10 .
1!
#292
0!
#294
b1 +
b0 $
1'
1!
#296
0!
#298
0'
b0 )
1(
0%
b10 +
1!
#300
0!
#302
b11 +
0(
1!
#304
0!
#306
b1000000 )
b100 +
1!
#308
0!
#310
b101 +
1%
1!
#312
0!
#314
b100000 *
b110 +
b0 ,
b1000000 .
1!
#316
0!
#318
b1 +
b1 $
1!
#320
0!
#322
b0 )
1(
0%
b10 +
1!
#324
0!
#326
b11 +
0(
1!
#328
0!
#330
b100000 )
b100 +
1!
#332
0!
#334
b101 +
1%
1!
#336
0!
#338
b10000 *
b110 +
b1 ,
b100000 .
1!
#340
0!
#342
b1 +
b10 $
1!
#344
0!
#346
b0 )
1(
0%
b10 +
1!
#348
0!
#350
b11 +
0(
1!
#352
0!
#354
b10000 )
b100 +
1!
#356
0!
#358
b101 +
1%
1!
#360
0!
#362
b1000 *
b110 +
b10 ,
b10000 .
1!
#364
0!
#366
b1 +
b11 $
1!
#368
0!
#370
b0 )
1(
0%
b10 +
1!
#372
0!
#374
b11 +
0(
1!
#376
0!
#378
b1000 )
b100 +
1!
#380
0!
#382
b101 +
1%
1!
#384
0!
#386
b100 *
b110 +
b11 ,
b1000 .
1!
#388
0!
#390
b1 +
b100 $
1!
#392
0!
#394
b0 )
1(
0%
b10 +
1!
#396
0!
#398
b11 +
0(
1!
#400
0!
#402
b100 )
b100 +
1!
#404
0!
#406
b101 +
1%
1!
#408
0!
#410
b10 *
b110 +
b100 ,
b100 .
1!
#412
0!
#414
b1 +
b101 $
1!
#416
0!
#418
b0 )
1(
0%
b10 +
1!
#420
0!
#422
b11 +
0(
1!
#424
0!
#426
b10 )
b100 +
1!
#428
0!
#430
b101 +
1%
1!
#432
0!
#434
b1000000 *
b110 +
b101 ,
b10 .
1!
#436
0!
#438
b1 +
b0 $
1'
1!
#440
0!
#442
0'
b0 )
1(
0%
b10 +
1!
#444
0!
#446
b11 +
0(
1!
